KaliLinuxWebShentouCeshiMiji/README.md
KaliLinuxWebShentouCeshiMiji/__init__.py
KaliLinuxWebShentouCeshiMiji/__main__.py
KaliLinuxWebShentouCeshiMiji/file.epub
KaliLinuxWebShentouCeshiMiji/index.html
KaliLinuxWebShentouCeshiMiji/css/__init__.py
KaliLinuxWebShentouCeshiMiji/css/annotations.css
KaliLinuxWebShentouCeshiMiji/css/main.css
KaliLinuxWebShentouCeshiMiji/css/normalize.css
KaliLinuxWebShentouCeshiMiji/css/popup.css
KaliLinuxWebShentouCeshiMiji/font/__init__.py
KaliLinuxWebShentouCeshiMiji/font/fontello.eot
KaliLinuxWebShentouCeshiMiji/font/fontello.svg
KaliLinuxWebShentouCeshiMiji/font/fontello.ttf
KaliLinuxWebShentouCeshiMiji/font/fontello.woff
KaliLinuxWebShentouCeshiMiji/img/__init__.py
KaliLinuxWebShentouCeshiMiji/img/annotator-glyph-sprite.png
KaliLinuxWebShentouCeshiMiji/img/annotator-icon-sprite.png
KaliLinuxWebShentouCeshiMiji/img/apple-touch-icon.png
KaliLinuxWebShentouCeshiMiji/img/cancelfullscreen.png
KaliLinuxWebShentouCeshiMiji/img/close.png
KaliLinuxWebShentouCeshiMiji/img/fullscreen.png
KaliLinuxWebShentouCeshiMiji/img/loader.gif
KaliLinuxWebShentouCeshiMiji/img/menu-icon.png
KaliLinuxWebShentouCeshiMiji/img/save.png
KaliLinuxWebShentouCeshiMiji/img/saved.png
KaliLinuxWebShentouCeshiMiji/img/settings-s.png
KaliLinuxWebShentouCeshiMiji/img/settings.png
KaliLinuxWebShentouCeshiMiji/img/star.png
KaliLinuxWebShentouCeshiMiji/js/__init__.py
KaliLinuxWebShentouCeshiMiji/js/epub.js
KaliLinuxWebShentouCeshiMiji/js/epub.min.js
KaliLinuxWebShentouCeshiMiji/js/epub.min.map
KaliLinuxWebShentouCeshiMiji/js/hooks.min.js
KaliLinuxWebShentouCeshiMiji/js/hooks.min.map
KaliLinuxWebShentouCeshiMiji/js/reader.js
KaliLinuxWebShentouCeshiMiji/js/reader.js.map
KaliLinuxWebShentouCeshiMiji/js/reader.min.js
KaliLinuxWebShentouCeshiMiji/js/reader.min.map
KaliLinuxWebShentouCeshiMiji/js/hooks/__init__.py
KaliLinuxWebShentouCeshiMiji/js/hooks/extensions/__init__.py
KaliLinuxWebShentouCeshiMiji/js/hooks/extensions/highlight.js
kali_linux_web_shentou_ceshi_miji-2024.3.1.0.dist-info/METADATA
kali_linux_web_shentou_ceshi_miji-2024.3.1.0.dist-info/WHEEL
kali_linux_web_shentou_ceshi_miji-2024.3.1.0.dist-info/entry_points.txt
kali_linux_web_shentou_ceshi_miji-2024.3.1.0.dist-info/top_level.txt
kali_linux_web_shentou_ceshi_miji-2024.3.1.0.dist-info/RECORD
